Metadata-Version: 2.1
Name: urdu2romanfromnlpd
Version: 0.0.2
Summary: A roman to urdu converter
Home-page: UNKNOWN
Author: Mohammad Ayyaz Azeem
Author-email: ayyaz.maju@gmail.com
License: MIT
Keywords: urdu2roman,roman
Platform: UNKNOWN
Classifier: Development Status :: 5 - Production/Stable
Classifier: Intended Audience :: Education
Classifier: License :: OSI Approved :: MIT License
Classifier: Programming Language :: Python :: 3
License-File: LICENCE.txt
